setup.py
wyn1/__init__.py
wyn1/wyn.py
wyn1.egg-info/PKG-INFO
wyn1.egg-info/SOURCES.txt
wyn1.egg-info/dependency_links.txt
wyn1.egg-info/top_level.txt