Metadata-Version: 2.1
Name: wyn1
Version: 1.0.0
Summary: sssssss
Author: dgw
Author-email: 535646343@qq.com
